{
  "className": "Tool",
  "ignoreUnknownInstances": true,
  "properties": {
    "RequiresHandle": true,
    "CanBeDropped": false,
    "ToolTip": "Rifle",
    "Grip": {
      "CFrame": {
        "position": [0, -0.307096, 1],
        "orientation": [[0.987299, -0.0350825, 0.154954], [0.0108147, 0.987893, 0.154758], [-0.158508, -0.151116, 0.975725]]
      }
    },
    "Attributes": {
      "Attributes": {
        "_ammo": { "Int32": 30 },
        "_reloading": { "Bool": false },
        "_reserveAmmo": { "Int32": 90 },
        "startingReserveAmmo": { "Int32": 90 },
        "pickupAmmoBonus": { "Int32": 30 },
        "maxReserveAmmo": { "Int32": 150 },
        "magazineSize": { "Int32": 30 },
        "fireMode": { "String": "Auto" },
        "rateOfFire": { "Float32": 600.0 },
        "damage": { "Float32": 10.0 },
        "range": { "Float32": 1000.0 },
        "raysPerShot": { "Int32": 1 },
        "rayRadius": { "Float32": 0.4 },
        "spread": { "Float32": 2.0 },
        "reloadTime": { "Float32": 1.5 },
        "recoilMin": { "Vector2": [0.0, 0.0] },
        "recoilMax": { "Vector2": [0.0, 0.0] },
        "aimAssistRange": { "Float32": 100.0 },
        "aimAssistFov": { "Float32": 20.0 },
        "aimAssistFrictionStrength": { "Float32": 0.5 },
        "aimAssistTrackingStrength": { "Float32": 0.5 },
        "aimAssistCenteringStrength": { "Float32": 0.0 },
        "viewModel": { "String": "Rifle" },
        "cameraModeFamily": { "String": "Rifle" },
        "unanchoredImpulseForce": { "Float32": 2.0 },
        "EnableFireRotation": { "Bool": true },
        "WeaponCategory": { "String": "Normal" },
        "WeaponIcon": { "String": "rbxthumb://type=Asset&id=117306764681731&w=420&h=420" }
      }
    }
  }
}
